package/__init__.py
package/example.py
krest_null_best-1.3.dist-info/LICENSE
krest_null_best-1.3.dist-info/METADATA
krest_null_best-1.3.dist-info/WHEEL
krest_null_best-1.3.dist-info/top_level.txt
krest_null_best-1.3.dist-info/RECORD
